cifar10_downloader/__init__.py
cifar10_web/__init__.py
cifar10_web-0.0.4.dist-info/METADATA
cifar10_web-0.0.4.dist-info/WHEEL
cifar10_web-0.0.4.dist-info/top_level.txt
cifar10_web-0.0.4.dist-info/RECORD
