Metadata-Version: 2.1
Name: cifar10-web
Version: 0.0.4
Summary: A package for obtaining data from CIFAR10
Home-page: https://github.com/QData/cifar10_web
Author: QData
Author-email: jm8wx@virginia.edu
License: UNKNOWN
Platform: UNKNOWN
Classifier: Programming Language :: Python :: 3
Classifier: License :: OSI Approved :: MIT License
Classifier: Operating System :: OS Independent
Requires-Python: >=3.6
